tnsa_api/__init__.py
tnsa_api/async_client.py
tnsa_api/client.py
tnsa_api/config.py
tnsa_api/demo.py
tnsa_api/example.py
tnsa_api/exceptions.py
tnsa_api/http_client.py
tnsa_api/install_package.py
tnsa_api/mcp_client.py
tnsa_api/setup.py
tnsa_api/test_client.py
tnsa_api/type_definitions.py
tnsa_api/upload_to_pypi.py
tnsa_api/web_search_client.py
tnsa_api/web_search_example.py
tnsa_api/models/__init__.py
tnsa_api/models/base.py
tnsa_api/models/chat.py
tnsa_api/models/common.py
tnsa_api/models/completion.py
tnsa_api/models/mcp.py
tnsa_api/models/streaming.py
tnsa_api/tools/__init__.py
tnsa_api/tools/web_search.py
tnsa_api-2.1.2.dist-info/METADATA
tnsa_api-2.1.2.dist-info/WHEEL
tnsa_api-2.1.2.dist-info/top_level.txt
tnsa_api-2.1.2.dist-info/RECORD
