Metadata-Version: 2.4
Name: tnsa-api
Version: 2.1.2
Summary: A powerful, OpenAI-compatible Python SDK for TNSA NGen3 Pro and Lite Models
Home-page: https://www.tnsaai.com
Author: TNSA AI
Author-email: TNSA AI <info@tnsaai.com>
Maintainer-email: TNSA AI <info@tnsaai.com>
License: MIT
Project-URL: Homepage, https://www.tnsaai.com
Project-URL: Documentation, https://docs.tnsaai.com
Project-URL: Repository, https://github.com/tnsaai/tnsa-api-python
Project-URL: Bug Tracker, https://github.com/tnsaai/tnsa-api-python/issues
Keywords: ai,api,tnsa,ngen3,llm,chat,completion
Classifier: Development Status :: 5 - Production/Stable
Classifier: Intended Audience :: Developers
Classifier: License :: OSI Approved :: MIT License
Classifier: Operating System :: OS Independent
Classifier: Programming Language :: Python :: 3
Classifier: Programming Language :: Python :: 3.8
Classifier: Programming Language :: Python :: 3.9
Classifier: Programming Language :: Python :: 3.10
Classifier: Programming Language :: Python :: 3.11
Classifier: Programming Language :: Python :: 3.12
Classifier: Topic :: Software Development :: Libraries :: Python Modules
Classifier: Topic :: Scientific/Engineering :: Artificial Intelligence
Requires-Python: >=3.8
Requires-Dist: requests>=2.25.0
Requires-Dist: aiohttp>=3.8.0
Requires-Dist: pydantic>=2.0.0
Requires-Dist: pyyaml>=6.0
Requires-Dist: typing-extensions>=4.0.0
Provides-Extra: dev
Requires-Dist: pytest>=7.0.0; extra == "dev"
Requires-Dist: pytest-asyncio>=0.21.0; extra == "dev"
Requires-Dist: pytest-cov>=4.0.0; extra == "dev"
Requires-Dist: black>=23.0.0; extra == "dev"
Requires-Dist: isort>=5.12.0; extra == "dev"
Requires-Dist: flake8>=6.0.0; extra == "dev"
Requires-Dist: mypy>=1.0.0; extra == "dev"
Requires-Dist: sphinx>=6.0.0; extra == "dev"
Requires-Dist: sphinx-rtd-theme>=1.2.0; extra == "dev"
Dynamic: author
Dynamic: home-page
Dynamic: requires-python
